KassOrm/__init__.py
KassOrm/Conn.py
KassOrm/Creator.py
KassOrm/Factory.py
KassOrm/Migration.py
KassOrm/Modelr.py
KassOrm/Querier.py
KassOrm/Seeder.py
KassOrm/stubs/__init__.py
KassOrm/stubs/migration_alter.stub
KassOrm/stubs/migration_create.stub
KassOrm/stubs/model.stub
kassorm-1.1.7.dist-info/LICENSE
kassorm-1.1.7.dist-info/METADATA
kassorm-1.1.7.dist-info/WHEEL
kassorm-1.1.7.dist-info/RECORD
