Metadata-Version: 2.1
Name: KassOrm
Version: 1.1.7
Summary: Gerenciador de banco de dados relacional
License: MIT
Author: kassiodouglas
Author-email: kass.doug@gmail.com
Requires-Python: >=3.11,<4.0
Classifier: Development Status :: 5 - Production/Stable
Classifier: License :: OSI Approved :: MIT License
Classifier: Natural Language :: Portuguese (Brazilian)
Classifier: Programming Language :: Python :: 3
Classifier: Programming Language :: Python :: 3.11
Classifier: Programming Language :: Python :: 3.12
Requires-Dist: faker (>=23.2.0,<24.0.0)
Requires-Dist: mysql (>=0.0.3,<0.0.4)
Requires-Dist: mysql-connector (>=2.2.9,<3.0.0)
Requires-Dist: mysql-connector-python (>=8.3.0,<9.0.0)
Requires-Dist: rich (>=13.7.0,<14.0.0)
